AUTHORS.md
HISTORY.md
LICENSE
minos/cli/__init__.py
minos/cli/__main__.py
minos/cli/api/__init__.py
minos/cli/api/new.py
minos/cli/api/set.py
minos/cli/api/utils.py
minos/cli/consoles.py
minos/cli/importlib.py
minos/cli/pathlib.py
minos/cli/templating/__init__.py
minos/cli/templating/fetchers.py
minos/cli/templating/processors.py
minos/cli/wizards/__init__.py
minos/cli/wizards/forms.py
minos/cli/wizards/questions.py
minos_cli-0.4.0.dist-info/entry_points.txt
minos_cli-0.4.0.dist-info/LICENSE
minos_cli-0.4.0.dist-info/WHEEL
minos_cli-0.4.0.dist-info/METADATA
minos_cli-0.4.0.dist-info/RECORD
