Metadata-Version: 2.1
Name: minos-cli
Version: 0.4.0
Summary: Command Line Interface for the Minos framework
Home-page: http://www.minos.run/
License: MIT
Keywords: clariteia,minos,microservice,cli
Author: Minos Framework Devs
Author-email: hey@minos.run
Requires-Python: >=3.9,<4.0
Classifier: Development Status :: 4 - Beta
Classifier: Intended Audience :: Developers
Classifier: License :: OSI Approved :: MIT License
Classifier: Natural Language :: English
Classifier: Programming Language :: Python :: 3
Classifier: Programming Language :: Python :: 3.10
Classifier: Programming Language :: Python :: 3.9
Requires-Dist: cached-property (>=1.5.2,<2.0.0)
Requires-Dist: copier (>=5.1.0,<6.0.0)
Requires-Dist: markupsafe (==2.0.1)
Requires-Dist: rich (>=10.14.0,<11.0.0)
Requires-Dist: typer (>=0.4.0,<0.5.0)
Project-URL: Repository, https://github.com/minos-framework/minos-cli
